sphinxcontrib_xlsxtable-1.1.1-py3.9-nspkg.pth
sphinxcontrib/xlsxtable/__init__.py
sphinxcontrib/xlsxtable/__main__.py
sphinxcontrib/xlsxtable/xlsx2gridtable.py
sphinxcontrib/xlsxtable/xlsxtable.py
sphinxcontrib/xlsxtable/workbook/__init__.py
sphinxcontrib/xlsxtable/workbook/workbook.py
sphinxcontrib_xlsxtable-1.1.1.dist-info/LICENSE
sphinxcontrib_xlsxtable-1.1.1.dist-info/METADATA
sphinxcontrib_xlsxtable-1.1.1.dist-info/WHEEL
sphinxcontrib_xlsxtable-1.1.1.dist-info/namespace_packages.txt
sphinxcontrib_xlsxtable-1.1.1.dist-info/top_level.txt
sphinxcontrib_xlsxtable-1.1.1.dist-info/RECORD
