Metadata-Version: 2.1
Name: sphinxcontrib-xlsxtable
Version: 1.1.1
Summary: A sphinx extension for making table from Excel file
Home-page: https://github.com/kkAyataka/sphinxcontrib-xlsxtable
Author: kkAyataka
Author-email: kk.ayataka@gmail.com
License: MIT
Download-URL: http://pypi.python.org/pypi/sphinxcontrib-xlsxtable
Platform: any
Classifier: Development Status :: 5 - Production/Stable
Classifier: Environment :: Console
Classifier: Environment :: Web Environment
Classifier: Intended Audience :: Developers
Classifier: License :: OSI Approved :: MIT License
Classifier: Operating System :: OS Independent
Classifier: Programming Language :: Python
Classifier: Programming Language :: Python :: 3.0
Classifier: Framework :: Sphinx :: Extension
Classifier: Topic :: Documentation
Classifier: Topic :: Utilities
License-File: LICENSE
Requires-Dist: Sphinx (>=2.0.0)
Requires-Dist: openpyxl (>=3.0.0)
